[{"line_id": 1, "canonical_id": "MV.1.1.1", "speaker": "ANTONIO", "text": "In sooth I know not why I am so sad."}, {"line_id": 2, "canonical_id": "MV.1.1.2", "speaker": "ANTONIO", "text": "It wearies me, you say it wearies you."}, {"line_id": 3, "canonical_id": "MV.1.1.3", "speaker": "ANTONIO", "text": "But how I caught it, found it, or came by it,"}, {"line_id": 4, "canonical_id": "MV.1.1.4", "speaker": "ANTONIO", "text": "What stuff ’tis made of, whereof it is born,"}, {"line_id": 5, "canonical_id": "MV.1.1.5", "speaker": "ANTONIO", "text": "I am to learn."}, {"line_id": 6, "canonical_id": "MV.1.1.6", "speaker": "ANTONIO", "text": "And such a want-wit sadness makes of me"}, {"line_id": 7, "canonical_id": "MV.1.1.7", "speaker": "ANTONIO", "text": "That I have much ado to know myself."}, {"line_id": 8, "canonical_id": "MV.1.1.8", "speaker": "SALARINO", "text": "Your mind is tossing on the ocean,"}, {"line_id": 9, "canonical_id": "MV.1.1.9", "speaker": "SALARINO", "text": "There where your argosies with portly sail"}, {"line_id": 10, "canonical_id": "MV.1.1.10", "speaker": "SALARINO", "text": "(Like signiors and rich burghers on the flood,"}, {"line_id": 11, "canonical_id": "MV.1.1.11", "speaker": "SALARINO", "text": "Or, as it were, the pageants of the sea)"}, {"line_id": 12, "canonical_id": "MV.1.1.12", "speaker": "SALARINO", "text": "Do overpeer the petty traffickers"}, {"line_id": 13, "canonical_id": "MV.1.1.13", "speaker": "SALARINO", "text": "That curtsy to them, do them reverence,"}, {"line_id": 14, "canonical_id": "MV.1.1.14", "speaker": "SALARINO", "text": "As they fly by them with their woven wings."}, {"line_id": 15, "canonical_id": "MV.1.1.15", "speaker": "SOLANIO", "text": "Believe me, sir, had I such venture forth,"}, {"line_id": 16, "canonical_id": "MV.1.1.16", "speaker": "SOLANIO", "text": "The better part of my affections would"}, {"line_id": 17, "canonical_id": "MV.1.1.17", "speaker": "SOLANIO", "text": "Be with my hopes abroad. I should be still"}, {"line_id": 18, "canonical_id": "MV.1.1.18", "speaker": "SOLANIO", "text": "Plucking the grass to know where sits the wind,"}, {"line_id": 19, "canonical_id": "MV.1.1.19", "speaker": "SOLANIO", "text": "Piring in maps for ports and piers and roads;"}, {"line_id": 20, "canonical_id": "MV.1.1.20", "speaker": "SOLANIO", "text": "And every object that might make me fear"}, {"line_id": 21, "canonical_id": "MV.1.1.21", "speaker": "SOLANIO", "text": "Misfortune to my ventures, out of doubt"}, {"line_id": 22, "canonical_id": "MV.1.1.22", "speaker": "SOLANIO", "text": "Would make me sad."}, {"line_id": 23, "canonical_id": "MV.1.1.23", "speaker": "SALARINO", "text": "My wind cooling my broth"}, {"line_id": 24, "canonical_id": "MV.1.1.24", "speaker": "SALARINO", "text": "Would blow me to an ague when I thought"}, {"line_id": 25, "canonical_id": "MV.1.1.25", "speaker": "SALARINO", "text": "What harm a wind too great might do at sea."}, {"line_id": 26, "canonical_id": "MV.1.1.26", "speaker": "SALARINO", "text": "I should not see the sandy hourglass run"}, {"line_id": 27, "canonical_id": "MV.1.1.27", "speaker": "SALARINO", "text": "But I should think of shallows and of flats,"}, {"line_id": 28, "canonical_id": "MV.1.1.28", "speaker": "SALARINO", "text": "And see my wealthy Andrew docked in sand,"}, {"line_id": 29, "canonical_id": "MV.1.1.29", "speaker": "SALARINO", "text": "Vailing her high top lower than her ribs"}, {"line_id": 30, "canonical_id": "MV.1.1.30", "speaker": "SALARINO", "text": "To kiss her burial. Should I go to church"}, {"line_id": 31, "canonical_id": "MV.1.1.31", "speaker": "SALARINO", "text": "And see the holy edifice of stone"}, {"line_id": 32, "canonical_id": "MV.1.1.32", "speaker": "SALARINO", "text": "And not bethink me straight of dangerous rocks,"}, {"line_id": 33, "canonical_id": "MV.1.1.33", "speaker": "SALARINO", "text": "Which, touching but my gentle vessel’s side,"}, {"line_id": 34, "canonical_id": "MV.1.1.34", "speaker": "SALARINO", "text": "Would scatter all her spices on the stream,"}, {"line_id": 35, "canonical_id": "MV.1.1.35", "speaker": "SALARINO", "text": "Enrobe the roaring waters with my silks,"}, {"line_id": 36, "canonical_id": "MV.1.1.36", "speaker": "SALARINO", "text": "And, in a word, but even now worth this"}, {"line_id": 37, "canonical_id": "MV.1.1.37", "speaker": "SALARINO", "text": "And now worth nothing? Shall I have the thought"}, {"line_id": 38, "canonical_id": "MV.1.1.38", "speaker": "SALARINO", "text": "To think on this, and shall I lack the thought"}, {"line_id": 39, "canonical_id": "MV.1.1.39", "speaker": "SALARINO", "text": "That such a thing bechanced would make me sad?"}, {"line_id": 40, "canonical_id": "MV.1.1.40", "speaker": "SALARINO", "text": "But tell not me: I know Antonio"}, {"line_id": 41, "canonical_id": "MV.1.1.41", "speaker": "SALARINO", "text": "Is sad to think upon his merchandise."}, {"line_id": 42, "canonical_id": "MV.1.1.42", "speaker": "ANTONIO", "text": "Believe me, no. I thank my fortune for it,"}, {"line_id": 43, "canonical_id": "MV.1.1.43", "speaker": "ANTONIO", "text": "My ventures are not in one bottom trusted,"}, {"line_id": 44, "canonical_id": "MV.1.1.44", "speaker": "ANTONIO", "text": "Nor to one place; nor is my whole estate"}, {"line_id": 45, "canonical_id": "MV.1.1.45", "speaker": "ANTONIO", "text": "Upon the fortune of this present year:"}, {"line_id": 46, "canonical_id": "MV.1.1.46", "speaker": "ANTONIO", "text": "Therefore my merchandise makes me not sad."}, {"line_id": 47, "canonical_id": "MV.1.1.47", "speaker": "SOLANIO", "text": "Why then you are in love."}, {"line_id": 48, "canonical_id": "MV.1.1.48", "speaker": "ANTONIO", "text": "Fie, fie!"}, {"line_id": 49, "canonical_id": "MV.1.1.49", "speaker": "SOLANIO", "text": "Not in love neither? Then let us say you are sad"}, {"line_id": 50, "canonical_id": "MV.1.1.50", "speaker": "SOLANIO", "text": "Because you are not merry; and ’twere as easy"}, {"line_id": 51, "canonical_id": "MV.1.1.51", "speaker": "SOLANIO", "text": "For you to laugh and leap, and say you are merry"}, {"line_id": 52, "canonical_id": "MV.1.1.52", "speaker": "SOLANIO", "text": "Because you are not sad. Now, by two-headed Janus,"}, {"line_id": 53, "canonical_id": "MV.1.1.53", "speaker": "SOLANIO", "text": "Nature hath framed strange fellows in her time:"}, {"line_id": 54, "canonical_id": "MV.1.1.54", "speaker": "SOLANIO", "text": "Some that will evermore peep through their eyes"}, {"line_id": 55, "canonical_id": "MV.1.1.55", "speaker": "SOLANIO", "text": "And laugh like parrots at a bagpiper,"}, {"line_id": 56, "canonical_id": "MV.1.1.56", "speaker": "SOLANIO", "text": "And other of such vinegar aspect"}, {"line_id": 57, "canonical_id": "MV.1.1.57", "speaker": "SOLANIO", "text": "That they’ll not show their teeth in way of smile"}, {"line_id": 58, "canonical_id": "MV.1.1.58", "speaker": "SOLANIO", "text": "Though Nestor swear the jest be laughable."}, {"line_id": 59, "canonical_id": "MV.1.1.59", "speaker": "SOLANIO", "text": "Here comes Bassanio, your most noble kinsman,"}, {"line_id": 60, "canonical_id": "MV.1.1.60", "speaker": "SOLANIO", "text": "Gratiano, and Lorenzo. Fare you well."}, {"line_id": 61, "canonical_id": "MV.1.1.61", "speaker": "SOLANIO", "text": "We leave you now with better company."}, {"line_id": 62, "canonical_id": "MV.1.1.62", "speaker": "SALARINO", "text": "I would have stayed till I had made you merry,"}, {"line_id": 63, "canonical_id": "MV.1.1.63", "speaker": "SALARINO", "text": "If worthier friends had not prevented me."}, {"line_id": 64, "canonical_id": "MV.1.1.64", "speaker": "ANTONIO", "text": "Your worth is very dear in my regard."}, {"line_id": 65, "canonical_id": "MV.1.1.65", "speaker": "ANTONIO", "text": "I take it your own business calls on you,"}, {"line_id": 66, "canonical_id": "MV.1.1.66", "speaker": "ANTONIO", "text": "And you embrace th’ occasion to depart."}, {"line_id": 67, "canonical_id": "MV.1.1.67", "speaker": "SALARINO", "text": "Good morrow, my good lords."}, {"line_id": 68, "canonical_id": "MV.1.1.68", "speaker": "BASSANIO", "text": "Good signiors both, when shall we laugh? Say, when?"}, {"line_id": 69, "canonical_id": "MV.1.1.69", "speaker": "BASSANIO", "text": "You grow exceeding strange. Must it be so?"}, {"line_id": 70, "canonical_id": "MV.1.1.70", "speaker": "SALARINO", "text": "We’ll make our leisures to attend on yours."}, {"line_id": 71, "canonical_id": "MV.1.1.71", "speaker": "LORENZO", "text": "My Lord Bassanio, since you have found Antonio,"}, {"line_id": 72, "canonical_id": "MV.1.1.72", "speaker": "LORENZO", "text": "We two will leave you. But at dinner time"}, {"line_id": 73, "canonical_id": "MV.1.1.73", "speaker": "LORENZO", "text": "I pray you have in mind where we must meet."}, {"line_id": 74, "canonical_id": "MV.1.1.74", "speaker": "BASSANIO", "text": "I will not fail you."}, {"line_id": 75, "canonical_id": "MV.1.1.75", "speaker": "GRATIANO", "text": "You look not well, Signior Antonio."}, {"line_id": 76, "canonical_id": "MV.1.1.76", "speaker": "GRATIANO", "text": "You have too much respect upon the world."}, {"line_id": 77, "canonical_id": "MV.1.1.77", "speaker": "GRATIANO", "text": "They lose it that do buy it with much care."}, {"line_id": 78, "canonical_id": "MV.1.1.78", "speaker": "GRATIANO", "text": "Believe me, you are marvelously changed."}, {"line_id": 79, "canonical_id": "MV.1.1.79", "speaker": "ANTONIO", "text": "I hold the world but as the world, Gratiano,"}, {"line_id": 80, "canonical_id": "MV.1.1.80", "speaker": "ANTONIO", "text": "A stage where every man must play a part,"}, {"line_id": 81, "canonical_id": "MV.1.1.81", "speaker": "ANTONIO", "text": "And mine a sad one."}, {"line_id": 82, "canonical_id": "MV.1.1.82", "speaker": "GRATIANO", "text": "Let me play the fool."}, {"line_id": 83, "canonical_id": "MV.1.1.83", "speaker": "GRATIANO", "text": "With mirth and laughter let old wrinkles come,"}, {"line_id": 84, "canonical_id": "MV.1.1.84", "speaker": "GRATIANO", "text": "And let my liver rather heat with wine"}, {"line_id": 85, "canonical_id": "MV.1.1.85", "speaker": "GRATIANO", "text": "Than my heart cool with mortifying groans."}, {"line_id": 86, "canonical_id": "MV.1.1.86", "speaker": "GRATIANO", "text": "Why should a man whose blood is warm within"}, {"line_id": 87, "canonical_id": "MV.1.1.87", "speaker": "GRATIANO", "text": "Sit like his grandsire cut in alabaster?"}, {"line_id": 88, "canonical_id": "MV.1.1.88", "speaker": "GRATIANO", "text": "Sleep when he wakes? And creep into the jaundice"}, {"line_id": 89, "canonical_id": "MV.1.1.89", "speaker": "GRATIANO", "text": "By being peevish? I tell thee what, Antonio"}, {"line_id": 90, "canonical_id": "MV.1.1.90", "speaker": "GRATIANO", "text": "(I love thee, and ’tis my love that speaks):"}, {"line_id": 91, "canonical_id": "MV.1.1.91", "speaker": "GRATIANO", "text": "There are a sort of men whose visages"}, {"line_id": 92, "canonical_id": "MV.1.1.92", "speaker": "GRATIANO", "text": "Do cream and mantle like a standing pond"}, {"line_id": 93, "canonical_id": "MV.1.1.93", "speaker": "GRATIANO", "text": "And do a willful stillness entertain"}, {"line_id": 94, "canonical_id": "MV.1.1.94", "speaker": "GRATIANO", "text": "With purpose to be dressed in an opinion"}, {"line_id": 95, "canonical_id": "MV.1.1.95", "speaker": "GRATIANO", "text": "Of wisdom, gravity, profound conceit,"}, {"line_id": 96, "canonical_id": "MV.1.1.96", "speaker": "GRATIANO", "text": "As who should say “I am Sir Oracle,"}, {"line_id": 97, "canonical_id": "MV.1.1.97", "speaker": "GRATIANO", "text": "And when I ope my lips, let no dog bark.”"}, {"line_id": 98, "canonical_id": "MV.1.1.98", "speaker": "GRATIANO", "text": "O my Antonio, I do know of these"}, {"line_id": 99, "canonical_id": "MV.1.1.99", "speaker": "GRATIANO", "text": "That therefore only are reputed wise"}, {"line_id": 100, "canonical_id": "MV.1.1.100", "speaker": "GRATIANO", "text": "For saying nothing, when, I am very sure,"}, {"line_id": 101, "canonical_id": "MV.1.1.101", "speaker": "GRATIANO", "text": "If they should speak, would almost damn those ears"}, {"line_id": 102, "canonical_id": "MV.1.1.102", "speaker": "GRATIANO", "text": "Which, hearing them, would call their brothers fools."}, {"line_id": 103, "canonical_id": "MV.1.1.103", "speaker": "GRATIANO", "text": "I’ll tell thee more of this another time."}, {"line_id": 104, "canonical_id": "MV.1.1.104", "speaker": "GRATIANO", "text": "But fish not with this melancholy bait"}, {"line_id": 105, "canonical_id": "MV.1.1.105", "speaker": "GRATIANO", "text": "For this fool gudgeon, this opinion.—"}, {"line_id": 106, "canonical_id": "MV.1.1.106", "speaker": "GRATIANO", "text": "Come, good Lorenzo.—Fare you well a while."}, {"line_id": 107, "canonical_id": "MV.1.1.107", "speaker": "GRATIANO", "text": "I’ll end my exhortation after dinner."}, {"line_id": 108, "canonical_id": "MV.1.1.108", "speaker": "LORENZO", "text": "Well, we will leave you then till dinner time."}, {"line_id": 109, "canonical_id": "MV.1.1.109", "speaker": "LORENZO", "text": "I must be one of these same dumb wise men,"}, {"line_id": 110, "canonical_id": "MV.1.1.110", "speaker": "LORENZO", "text": "For Gratiano never lets me speak."}, {"line_id": 111, "canonical_id": "MV.1.1.111", "speaker": "GRATIANO", "text": "Well, keep me company but two years more,"}, {"line_id": 112, "canonical_id": "MV.1.1.112", "speaker": "GRATIANO", "text": "Thou shalt not know the sound of thine own tongue."}, {"line_id": 113, "canonical_id": "MV.1.1.113", "speaker": "ANTONIO", "text": "Fare you well. I’ll grow a talker for this gear."}, {"line_id": 114, "canonical_id": "MV.1.1.114", "speaker": "GRATIANO", "text": "Thanks, i’ faith, for silence is only commendable"}, {"line_id": 115, "canonical_id": "MV.1.1.115", "speaker": "GRATIANO", "text": "In a neat’s tongue dried and a maid not vendible."}, {"line_id": 116, "canonical_id": "MV.1.1.116", "speaker": "ANTONIO", "text": "Is that anything now?"}, {"line_id": 117, "canonical_id": "MV.1.1.117", "speaker": "BASSANIO", "text": "Gratiano speaks an infinite deal of nothing,"}, {"line_id": 118, "canonical_id": "MV.1.1.118", "speaker": "BASSANIO", "text": "more than any man in all Venice. His reasons are as"}, {"line_id": 119, "canonical_id": "MV.1.1.119", "speaker": "BASSANIO", "text": "two grains of wheat hid in two bushels of chaff: you"}, {"line_id": 120, "canonical_id": "MV.1.1.120", "speaker": "BASSANIO", "text": "shall seek all day ere you find them, and when you"}, {"line_id": 121, "canonical_id": "MV.1.1.121", "speaker": "BASSANIO", "text": "have them, they are not worth the search."}, {"line_id": 122, "canonical_id": "MV.1.1.122", "speaker": "ANTONIO", "text": "Well, tell me now what lady is the same"}, {"line_id": 123, "canonical_id": "MV.1.1.123", "speaker": "ANTONIO", "text": "To whom you swore a secret pilgrimage,"}, {"line_id": 124, "canonical_id": "MV.1.1.124", "speaker": "ANTONIO", "text": "That you today promised to tell me of?"}, {"line_id": 125, "canonical_id": "MV.1.1.125", "speaker": "BASSANIO", "text": "’Tis not unknown to you, Antonio,"}, {"line_id": 126, "canonical_id": "MV.1.1.126", "speaker": "BASSANIO", "text": "How much I have disabled mine estate"}, {"line_id": 127, "canonical_id": "MV.1.1.127", "speaker": "BASSANIO", "text": "By something showing a more swelling port"}, {"line_id": 128, "canonical_id": "MV.1.1.128", "speaker": "BASSANIO", "text": "Than my faint means would grant continuance."}, {"line_id": 129, "canonical_id": "MV.1.1.129", "speaker": "BASSANIO", "text": "Nor do I now make moan to be abridged"}, {"line_id": 130, "canonical_id": "MV.1.1.130", "speaker": "BASSANIO", "text": "From such a noble rate. But my chief care"}, {"line_id": 131, "canonical_id": "MV.1.1.131", "speaker": "BASSANIO", "text": "Is to come fairly off from the great debts"}, {"line_id": 132, "canonical_id": "MV.1.1.132", "speaker": "BASSANIO", "text": "Wherein my time, something too prodigal,"}, {"line_id": 133, "canonical_id": "MV.1.1.133", "speaker": "BASSANIO", "text": "Hath left me gaged. To you, Antonio,"}, {"line_id": 134, "canonical_id": "MV.1.1.134", "speaker": "BASSANIO", "text": "I owe the most in money and in love,"}, {"line_id": 135, "canonical_id": "MV.1.1.135", "speaker": "BASSANIO", "text": "And from your love I have a warranty"}, {"line_id": 136, "canonical_id": "MV.1.1.136", "speaker": "BASSANIO", "text": "To unburden all my plots and purposes"}, {"line_id": 137, "canonical_id": "MV.1.1.137", "speaker": "BASSANIO", "text": "How to get clear of all the debts I owe."}, {"line_id": 138, "canonical_id": "MV.1.1.138", "speaker": "ANTONIO", "text": "I pray you, good Bassanio, let me know it;"}, {"line_id": 139, "canonical_id": "MV.1.1.139", "speaker": "ANTONIO", "text": "And if it stand, as you yourself still do,"}, {"line_id": 140, "canonical_id": "MV.1.1.140", "speaker": "ANTONIO", "text": "Within the eye of honor, be assured"}, {"line_id": 141, "canonical_id": "MV.1.1.141", "speaker": "ANTONIO", "text": "My purse, my person, my extremest means"}, {"line_id": 142, "canonical_id": "MV.1.1.142", "speaker": "ANTONIO", "text": "Lie all unlocked to your occasions."}, {"line_id": 143, "canonical_id": "MV.1.1.143", "speaker": "BASSANIO", "text": "In my school days, when I had lost one shaft,"}, {"line_id": 144, "canonical_id": "MV.1.1.144", "speaker": "BASSANIO", "text": "I shot his fellow of the selfsame flight"}, {"line_id": 145, "canonical_id": "MV.1.1.145", "speaker": "BASSANIO", "text": "The selfsame way with more advisèd watch"}, {"line_id": 146, "canonical_id": "MV.1.1.146", "speaker": "BASSANIO", "text": "To find the other forth; and by adventuring both"}, {"line_id": 147, "canonical_id": "MV.1.1.147", "speaker": "BASSANIO", "text": "I oft found both. I urge this childhood proof"}, {"line_id": 148, "canonical_id": "MV.1.1.148", "speaker": "BASSANIO", "text": "Because what follows is pure innocence."}, {"line_id": 149, "canonical_id": "MV.1.1.149", "speaker": "BASSANIO", "text": "I owe you much, and, like a willful youth,"}, {"line_id": 150, "canonical_id": "MV.1.1.150", "speaker": "BASSANIO", "text": "That which I owe is lost. But if you please"}, {"line_id": 151, "canonical_id": "MV.1.1.151", "speaker": "BASSANIO", "text": "To shoot another arrow that self way"}, {"line_id": 152, "canonical_id": "MV.1.1.152", "speaker": "BASSANIO", "text": "Which you did shoot the first, I do not doubt,"}, {"line_id": 153, "canonical_id": "MV.1.1.153", "speaker": "BASSANIO", "text": "As I will watch the aim, or to find both"}, {"line_id": 154, "canonical_id": "MV.1.1.154", "speaker": "BASSANIO", "text": "Or bring your latter hazard back again,"}, {"line_id": 155, "canonical_id": "MV.1.1.155", "speaker": "BASSANIO", "text": "And thankfully rest debtor for the first."}, {"line_id": 156, "canonical_id": "MV.1.1.156", "speaker": "ANTONIO", "text": "You know me well, and herein spend but time"}, {"line_id": 157, "canonical_id": "MV.1.1.157", "speaker": "ANTONIO", "text": "To wind about my love with circumstance;"}, {"line_id": 158, "canonical_id": "MV.1.1.158", "speaker": "ANTONIO", "text": "And out of doubt you do me now more wrong"}, {"line_id": 159, "canonical_id": "MV.1.1.159", "speaker": "ANTONIO", "text": "In making question of my uttermost"}, {"line_id": 160, "canonical_id": "MV.1.1.160", "speaker": "ANTONIO", "text": "Than if you had made waste of all I have."}, {"line_id": 161, "canonical_id": "MV.1.1.161", "speaker": "ANTONIO", "text": "Then do but say to me what I should do"}, {"line_id": 162, "canonical_id": "MV.1.1.162", "speaker": "ANTONIO", "text": "That in your knowledge may by me be done,"}, {"line_id": 163, "canonical_id": "MV.1.1.163", "speaker": "ANTONIO", "text": "And I am prest unto it. Therefore speak."}, {"line_id": 164, "canonical_id": "MV.1.1.164", "speaker": "BASSANIO", "text": "In Belmont is a lady richly left,"}, {"line_id": 165, "canonical_id": "MV.1.1.165", "speaker": "BASSANIO", "text": "And she is fair, and, fairer than that word,"}, {"line_id": 166, "canonical_id": "MV.1.1.166", "speaker": "BASSANIO", "text": "Of wondrous virtues. Sometimes from her eyes"}, {"line_id": 167, "canonical_id": "MV.1.1.167", "speaker": "BASSANIO", "text": "I did receive fair speechless messages."}, {"line_id": 168, "canonical_id": "MV.1.1.168", "speaker": "BASSANIO", "text": "Her name is Portia, nothing undervalued"}, {"line_id": 169, "canonical_id": "MV.1.1.169", "speaker": "BASSANIO", "text": "To Cato’s daughter, Brutus’ Portia."}, {"line_id": 170, "canonical_id": "MV.1.1.170", "speaker": "BASSANIO", "text": "Nor is the wide world ignorant of her worth,"}, {"line_id": 171, "canonical_id": "MV.1.1.171", "speaker": "BASSANIO", "text": "For the four winds blow in from every coast"}, {"line_id": 172, "canonical_id": "MV.1.1.172", "speaker": "BASSANIO", "text": "Renownèd suitors, and her sunny locks"}, {"line_id": 173, "canonical_id": "MV.1.1.173", "speaker": "BASSANIO", "text": "Hang on her temples like a golden fleece,"}, {"line_id": 174, "canonical_id": "MV.1.1.174", "speaker": "BASSANIO", "text": "Which makes her seat of Belmont Colchos’ strond,"}, {"line_id": 175, "canonical_id": "MV.1.1.175", "speaker": "BASSANIO", "text": "And many Jasons come in quest of her."}, {"line_id": 176, "canonical_id": "MV.1.1.176", "speaker": "BASSANIO", "text": "O my Antonio, had I but the means"}, {"line_id": 177, "canonical_id": "MV.1.1.177", "speaker": "BASSANIO", "text": "To hold a rival place with one of them,"}, {"line_id": 178, "canonical_id": "MV.1.1.178", "speaker": "BASSANIO", "text": "I have a mind presages me such thrift"}, {"line_id": 179, "canonical_id": "MV.1.1.179", "speaker": "BASSANIO", "text": "That I should questionless be fortunate!"}, {"line_id": 180, "canonical_id": "MV.1.1.180", "speaker": "ANTONIO", "text": "Thou know’st that all my fortunes are at sea;"}, {"line_id": 181, "canonical_id": "MV.1.1.181", "speaker": "ANTONIO", "text": "Neither have I money nor commodity"}, {"line_id": 182, "canonical_id": "MV.1.1.182", "speaker": "ANTONIO", "text": "To raise a present sum. Therefore go forth:"}, {"line_id": 183, "canonical_id": "MV.1.1.183", "speaker": "ANTONIO", "text": "Try what my credit can in Venice do;"}, {"line_id": 184, "canonical_id": "MV.1.1.184", "speaker": "ANTONIO", "text": "That shall be racked even to the uttermost"}, {"line_id": 185, "canonical_id": "MV.1.1.185", "speaker": "ANTONIO", "text": "To furnish thee to Belmont to fair Portia."}, {"line_id": 186, "canonical_id": "MV.1.1.186", "speaker": "ANTONIO", "text": "Go presently inquire, and so will I,"}, {"line_id": 187, "canonical_id": "MV.1.1.187", "speaker": "ANTONIO", "text": "Where money is, and I no question make"}, {"line_id": 188, "canonical_id": "MV.1.1.188", "speaker": "ANTONIO", "text": "To have it of my trust, or for my sake."}]