[{"line_id": 1, "canonical_id": "TGV.2.7.1", "speaker": "JULIA", "text": "Counsel, Lucetta. Gentle girl, assist me;"}, {"line_id": 2, "canonical_id": "TGV.2.7.2", "speaker": "JULIA", "text": "And ev’n in kind love I do conjure thee—"}, {"line_id": 3, "canonical_id": "TGV.2.7.3", "speaker": "JULIA", "text": "Who art the table wherein all my thoughts"}, {"line_id": 4, "canonical_id": "TGV.2.7.4", "speaker": "JULIA", "text": "Are visibly charactered and engraved—"}, {"line_id": 5, "canonical_id": "TGV.2.7.5", "speaker": "JULIA", "text": "To lesson me and tell me some good mean"}, {"line_id": 6, "canonical_id": "TGV.2.7.6", "speaker": "JULIA", "text": "How with my honor I may undertake"}, {"line_id": 7, "canonical_id": "TGV.2.7.7", "speaker": "JULIA", "text": "A journey to my loving Proteus."}, {"line_id": 8, "canonical_id": "TGV.2.7.8", "speaker": "LUCETTA", "text": "Alas, the way is wearisome and long."}, {"line_id": 9, "canonical_id": "TGV.2.7.9", "speaker": "JULIA", "text": "A true-devoted pilgrim is not weary"}, {"line_id": 10, "canonical_id": "TGV.2.7.10", "speaker": "JULIA", "text": "To measure kingdoms with his feeble steps;"}, {"line_id": 11, "canonical_id": "TGV.2.7.11", "speaker": "JULIA", "text": "Much less shall she that hath Love’s wings to fly,"}, {"line_id": 12, "canonical_id": "TGV.2.7.12", "speaker": "JULIA", "text": "And when the flight is made to one so dear,"}, {"line_id": 13, "canonical_id": "TGV.2.7.13", "speaker": "JULIA", "text": "Of such divine perfection, as Sir Proteus."}, {"line_id": 14, "canonical_id": "TGV.2.7.14", "speaker": "LUCETTA", "text": "Better forbear till Proteus make return."}, {"line_id": 15, "canonical_id": "TGV.2.7.15", "speaker": "JULIA", "text": "O, know’st thou not his looks are my soul’s food?"}, {"line_id": 16, "canonical_id": "TGV.2.7.16", "speaker": "JULIA", "text": "Pity the dearth that I have pinèd in"}, {"line_id": 17, "canonical_id": "TGV.2.7.17", "speaker": "JULIA", "text": "By longing for that food so long a time."}, {"line_id": 18, "canonical_id": "TGV.2.7.18", "speaker": "JULIA", "text": "Didst thou but know the inly touch of love,"}, {"line_id": 19, "canonical_id": "TGV.2.7.19", "speaker": "JULIA", "text": "Thou wouldst as soon go kindle fire with snow"}, {"line_id": 20, "canonical_id": "TGV.2.7.20", "speaker": "JULIA", "text": "As seek to quench the fire of love with words."}, {"line_id": 21, "canonical_id": "TGV.2.7.21", "speaker": "LUCETTA", "text": "I do not seek to quench your love’s hot fire,"}, {"line_id": 22, "canonical_id": "TGV.2.7.22", "speaker": "LUCETTA", "text": "But qualify the fire’s extreme rage,"}, {"line_id": 23, "canonical_id": "TGV.2.7.23", "speaker": "LUCETTA", "text": "Lest it should burn above the bounds of reason."}, {"line_id": 24, "canonical_id": "TGV.2.7.24", "speaker": "JULIA", "text": "The more thou damm’st it up, the more it burns."}, {"line_id": 25, "canonical_id": "TGV.2.7.25", "speaker": "JULIA", "text": "The current that with gentle murmur glides,"}, {"line_id": 26, "canonical_id": "TGV.2.7.26", "speaker": "JULIA", "text": "Thou know’st, being stopped, impatiently doth rage,"}, {"line_id": 27, "canonical_id": "TGV.2.7.27", "speaker": "JULIA", "text": "But when his fair course is not hinderèd,"}, {"line_id": 28, "canonical_id": "TGV.2.7.28", "speaker": "JULIA", "text": "He makes sweet music with th’ enameled stones,"}, {"line_id": 29, "canonical_id": "TGV.2.7.29", "speaker": "JULIA", "text": "Giving a gentle kiss to every sedge"}, {"line_id": 30, "canonical_id": "TGV.2.7.30", "speaker": "JULIA", "text": "He overtaketh in his pilgrimage;"}, {"line_id": 31, "canonical_id": "TGV.2.7.31", "speaker": "JULIA", "text": "And so by many winding nooks he strays"}, {"line_id": 32, "canonical_id": "TGV.2.7.32", "speaker": "JULIA", "text": "With willing sport to the wild ocean."}, {"line_id": 33, "canonical_id": "TGV.2.7.33", "speaker": "JULIA", "text": "Then let me go and hinder not my course."}, {"line_id": 34, "canonical_id": "TGV.2.7.34", "speaker": "JULIA", "text": "I’ll be as patient as a gentle stream"}, {"line_id": 35, "canonical_id": "TGV.2.7.35", "speaker": "JULIA", "text": "And make a pastime of each weary step"}, {"line_id": 36, "canonical_id": "TGV.2.7.36", "speaker": "JULIA", "text": "Till the last step have brought me to my love,"}, {"line_id": 37, "canonical_id": "TGV.2.7.37", "speaker": "JULIA", "text": "And there I’ll rest as after much turmoil"}, {"line_id": 38, "canonical_id": "TGV.2.7.38", "speaker": "JULIA", "text": "A blessèd soul doth in Elysium."}, {"line_id": 39, "canonical_id": "TGV.2.7.39", "speaker": "LUCETTA", "text": "But in what habit will you go along?"}, {"line_id": 40, "canonical_id": "TGV.2.7.40", "speaker": "JULIA", "text": "Not like a woman, for I would prevent"}, {"line_id": 41, "canonical_id": "TGV.2.7.41", "speaker": "JULIA", "text": "The loose encounters of lascivious men."}, {"line_id": 42, "canonical_id": "TGV.2.7.42", "speaker": "JULIA", "text": "Gentle Lucetta, fit me with such weeds"}, {"line_id": 43, "canonical_id": "TGV.2.7.43", "speaker": "JULIA", "text": "As may beseem some well-reputed page."}, {"line_id": 44, "canonical_id": "TGV.2.7.44", "speaker": "LUCETTA", "text": "Why, then, your Ladyship must cut your hair."}, {"line_id": 45, "canonical_id": "TGV.2.7.45", "speaker": "JULIA", "text": "No, girl, I’ll knit it up in silken strings"}, {"line_id": 46, "canonical_id": "TGV.2.7.46", "speaker": "JULIA", "text": "With twenty odd-conceited true-love knots."}, {"line_id": 47, "canonical_id": "TGV.2.7.47", "speaker": "JULIA", "text": "To be fantastic may become a youth"}, {"line_id": 48, "canonical_id": "TGV.2.7.48", "speaker": "JULIA", "text": "Of greater time than I shall show to be."}, {"line_id": 49, "canonical_id": "TGV.2.7.49", "speaker": "LUCETTA", "text": "What fashion, madam, shall I make your breeches?"}, {"line_id": 50, "canonical_id": "TGV.2.7.50", "speaker": "JULIA", "text": "That fits as well as “Tell me, good my lord,"}, {"line_id": 51, "canonical_id": "TGV.2.7.51", "speaker": "JULIA", "text": "What compass will you wear your farthingale?”"}, {"line_id": 52, "canonical_id": "TGV.2.7.52", "speaker": "JULIA", "text": "Why, ev’n what fashion thou best likes, Lucetta."}, {"line_id": 53, "canonical_id": "TGV.2.7.53", "speaker": "LUCETTA", "text": "You must needs have them with a codpiece, madam."}, {"line_id": 54, "canonical_id": "TGV.2.7.54", "speaker": "JULIA", "text": "Out, out, Lucetta. That will be ill-favored."}, {"line_id": 55, "canonical_id": "TGV.2.7.55", "speaker": "LUCETTA", "text": "A round hose, madam, now’s not worth a pin"}, {"line_id": 56, "canonical_id": "TGV.2.7.56", "speaker": "LUCETTA", "text": "Unless you have a codpiece to stick pins on."}, {"line_id": 57, "canonical_id": "TGV.2.7.57", "speaker": "JULIA", "text": "Lucetta, as thou lov’st me, let me have"}, {"line_id": 58, "canonical_id": "TGV.2.7.58", "speaker": "JULIA", "text": "What thou think’st meet and is most mannerly."}, {"line_id": 59, "canonical_id": "TGV.2.7.59", "speaker": "JULIA", "text": "But tell me, wench, how will the world repute me"}, {"line_id": 60, "canonical_id": "TGV.2.7.60", "speaker": "JULIA", "text": "For undertaking so unstaid a journey?"}, {"line_id": 61, "canonical_id": "TGV.2.7.61", "speaker": "JULIA", "text": "I fear me it will make me scandalized."}, {"line_id": 62, "canonical_id": "TGV.2.7.62", "speaker": "LUCETTA", "text": "If you think so, then stay at home and go not."}, {"line_id": 63, "canonical_id": "TGV.2.7.63", "speaker": "JULIA", "text": "Nay, that I will not."}, {"line_id": 64, "canonical_id": "TGV.2.7.64", "speaker": "LUCETTA", "text": "Then never dream on infamy, but go."}, {"line_id": 65, "canonical_id": "TGV.2.7.65", "speaker": "LUCETTA", "text": "If Proteus like your journey when you come,"}, {"line_id": 66, "canonical_id": "TGV.2.7.66", "speaker": "LUCETTA", "text": "No matter who’s displeased when you are gone."}, {"line_id": 67, "canonical_id": "TGV.2.7.67", "speaker": "LUCETTA", "text": "I fear me he will scarce be pleased withal."}, {"line_id": 68, "canonical_id": "TGV.2.7.68", "speaker": "JULIA", "text": "That is the least, Lucetta, of my fear."}, {"line_id": 69, "canonical_id": "TGV.2.7.69", "speaker": "JULIA", "text": "A thousand oaths, an ocean of his tears,"}, {"line_id": 70, "canonical_id": "TGV.2.7.70", "speaker": "JULIA", "text": "And instances of infinite of love"}, {"line_id": 71, "canonical_id": "TGV.2.7.71", "speaker": "JULIA", "text": "Warrant me welcome to my Proteus."}, {"line_id": 72, "canonical_id": "TGV.2.7.72", "speaker": "LUCETTA", "text": "All these are servants to deceitful men."}, {"line_id": 73, "canonical_id": "TGV.2.7.73", "speaker": "JULIA", "text": "Base men that use them to so base effect!"}, {"line_id": 74, "canonical_id": "TGV.2.7.74", "speaker": "JULIA", "text": "But truer stars did govern Proteus’ birth."}, {"line_id": 75, "canonical_id": "TGV.2.7.75", "speaker": "JULIA", "text": "His words are bonds, his oaths are oracles,"}, {"line_id": 76, "canonical_id": "TGV.2.7.76", "speaker": "JULIA", "text": "His love sincere, his thoughts immaculate,"}, {"line_id": 77, "canonical_id": "TGV.2.7.77", "speaker": "JULIA", "text": "His tears pure messengers sent from his heart,"}, {"line_id": 78, "canonical_id": "TGV.2.7.78", "speaker": "JULIA", "text": "His heart as far from fraud as heaven from Earth."}, {"line_id": 79, "canonical_id": "TGV.2.7.79", "speaker": "LUCETTA", "text": "Pray heav’n he prove so when you come to him."}, {"line_id": 80, "canonical_id": "TGV.2.7.80", "speaker": "JULIA", "text": "Now, as thou lov’st me, do him not that wrong"}, {"line_id": 81, "canonical_id": "TGV.2.7.81", "speaker": "JULIA", "text": "To bear a hard opinion of his truth."}, {"line_id": 82, "canonical_id": "TGV.2.7.82", "speaker": "JULIA", "text": "Only deserve my love by loving him."}, {"line_id": 83, "canonical_id": "TGV.2.7.83", "speaker": "JULIA", "text": "And presently go with me to my chamber"}, {"line_id": 84, "canonical_id": "TGV.2.7.84", "speaker": "JULIA", "text": "To take a note of what I stand in need of"}, {"line_id": 85, "canonical_id": "TGV.2.7.85", "speaker": "JULIA", "text": "To furnish me upon my longing journey."}, {"line_id": 86, "canonical_id": "TGV.2.7.86", "speaker": "JULIA", "text": "All that is mine I leave at thy dispose,"}, {"line_id": 87, "canonical_id": "TGV.2.7.87", "speaker": "JULIA", "text": "My goods, my lands, my reputation."}, {"line_id": 88, "canonical_id": "TGV.2.7.88", "speaker": "JULIA", "text": "Only, in lieu thereof, dispatch me hence."}, {"line_id": 89, "canonical_id": "TGV.2.7.89", "speaker": "JULIA", "text": "Come, answer not, but to it presently."}, {"line_id": 90, "canonical_id": "TGV.2.7.90", "speaker": "JULIA", "text": "I am impatient of my tarriance."}]